ppm_fhir/__init__.py
ppm_fhir/fhir_resources.py
ppm_fhir/fhir_response_processing.py
ppm_fhir/fhir_services.py
ppm_fhir-0.3.10.dist-info/DESCRIPTION.rst
ppm_fhir-0.3.10.dist-info/METADATA
ppm_fhir-0.3.10.dist-info/RECORD
ppm_fhir-0.3.10.dist-info/WHEEL
ppm_fhir-0.3.10.dist-info/metadata.json
ppm_fhir-0.3.10.dist-info/top_level.txt
