Metadata-Version: 2.0
Name: ppm-fhir
Version: 0.3.10
Summary: A library to facilitate handling of FHIR data in the PPM project.
Home-page: https://github.com/hms-dbmi/ppm-fhir
Author: UNKNOWN
Author-email: UNKNOWN
License: UNKNOWN
Download-URL: https://github.com/hms-dbmi/ppm-fhir/tarball/0.3.4
Platform: UNKNOWN
Requires-Dist: requests
Requires-Dist: fhirclient (==3.0.0)
Requires-Dist: furl
